minppo/__init__.py
minppo/config.py
minppo/environment.py
minppo/infer.py
minppo/py.typed
minppo/train.py
minppo-0.0.1.dist-info/LICENSE
minppo-0.0.1.dist-info/METADATA
minppo-0.0.1.dist-info/WHEEL
minppo-0.0.1.dist-info/top_level.txt
minppo-0.0.1.dist-info/RECORD
